{
  "Id": "2ef59e03-373c-4799-8e13-172dcf0306ce",
  "Name": "MaterialStockLockShipment",
  "OriginalName": "MaterialStockLockShipment",
  "NamePlural": "MaterialStockLockShipments",
  "DatabaseTableName": "MaterialStock_LockShipment",
  "Namespace": "MaterialStockLockShipments",
  "Type": 1,
  "MasterEntityName": null,
  "MasterEntity": null,
  "BaseClass": "FullAuditedAggregateRoot",
  "PageTitle": "MaterialStockLockShipments",
  "MenuIcon": "file-alt",
  "PrimaryKeyType": "Guid",
  "PreserveCustomCode": false,
  "IsMultiTenant": false,
  "CheckConcurrency": false,
  "BulkDeleteEnabled": false,
  "ShouldCreateUserInterface": false,
  "ShouldCreateBackend": true,
  "ShouldExportExcel": false,
  "ShouldAddMigration": false,
  "ShouldUpdateDatabase": false,
  "CreateTests": false,
  "Properties": [
    {
      "Id": "ff84241b-5a5b-4dfb-b435-badff625fbf0",
      "Name": "GolfaCode",
      "Type": "string",
      "EnumType": null,
      "EnumNamespace": null,
      "EnumAngularImport": null,
      "EnumFilePath": null,
      "DefaultValue": null,
      "IsNullable": false,
      "IsRequired": true,
      "IsFilterable": true,
      "AllowEmptyStrings": false,
      "IsTextArea": false,
      "MinLength": null,
      "MaxLength": 50,
      "SortOrder": 0,
      "SortType": 0,
      "Regex": null,
      "EmailValidation": false,
      "ShowOnList": true,
      "ShowOnCreateModal": true,
      "ShowOnEditModal": true,
      "ReadonlyOnEditModal": false,
      "EnumValues": null,
      "IsSelected": true,
      "MaxFileSize": null,
      "OrdinalIndex": 1
    },
    {
      "Id": "51c0ab7e-3092-43df-9266-ae1346885907",
      "Name": "LockOnOrder",
      "Type": "int",
      "EnumType": null,
      "EnumNamespace": null,
      "EnumAngularImport": null,
      "EnumFilePath": null,
      "DefaultValue": null,
      "IsNullable": true,
      "IsRequired": false,
      "IsFilterable": true,
      "AllowEmptyStrings": false,
      "IsTextArea": false,
      "MinLength": null,
      "MaxLength": null,
      "SortOrder": 0,
      "SortType": 0,
      "Regex": null,
      "EmailValidation": false,
      "ShowOnList": true,
      "ShowOnCreateModal": true,
      "ShowOnEditModal": true,
      "ReadonlyOnEditModal": false,
      "EnumValues": null,
      "IsSelected": true,
      "MaxFileSize": null,
      "OrdinalIndex": 2
    },
    {
      "Id": "814fa0ea-a0e7-4dd8-8132-fd34af81fa0f",
      "Name": "StockOnOrder",
      "Type": "int",
      "EnumType": null,
      "EnumNamespace": null,
      "EnumAngularImport": null,
      "EnumFilePath": null,
      "DefaultValue": null,
      "IsNullable": true,
      "IsRequired": false,
      "IsFilterable": true,
      "AllowEmptyStrings": false,
      "IsTextArea": false,
      "MinLength": null,
      "MaxLength": null,
      "SortOrder": 0,
      "SortType": 0,
      "Regex": null,
      "EmailValidation": false,
      "ShowOnList": true,
      "ShowOnCreateModal": true,
      "ShowOnEditModal": true,
      "ReadonlyOnEditModal": false,
      "EnumValues": null,
      "IsSelected": true,
      "MaxFileSize": null,
      "OrdinalIndex": 3
    },
    {
      "Id": "a1efb72c-2a5a-42f2-9842-3ac16f4c3fa0",
      "Name": "Note",
      "Type": "string",
      "EnumType": null,
      "EnumNamespace": null,
      "EnumAngularImport": null,
      "EnumFilePath": null,
      "DefaultValue": null,
      "IsNullable": true,
      "IsRequired": false,
      "IsFilterable": true,
      "AllowEmptyStrings": false,
      "IsTextArea": false,
      "MinLength": null,
      "MaxLength": 4000,
      "SortOrder": 0,
      "SortType": 0,
      "Regex": null,
      "EmailValidation": false,
      "ShowOnList": true,
      "ShowOnCreateModal": true,
      "ShowOnEditModal": true,
      "ReadonlyOnEditModal": false,
      "EnumValues": null,
      "IsSelected": true,
      "MaxFileSize": null,
      "OrdinalIndex": 4
    }
  ],
  "NavigationProperties": [],
  "NavigationConnections": [],
  "ChildEntities": [],
  "PhysicalFileName": "MaterialStockLockShipment.json"
}